pytest_robotframework/__init__.py
pytest_robotframework/_internal/__init__.py
pytest_robotframework/_internal/cringe_globals.py
pytest_robotframework/_internal/errors.py
pytest_robotframework/_internal/pytest/__init__.py
pytest_robotframework/_internal/pytest/exception_getter.py
pytest_robotframework/_internal/pytest/hooks.py
pytest_robotframework/_internal/pytest/plugin.py
pytest_robotframework/_internal/pytest/robot_file_support.py
pytest_robotframework/_internal/pytest/xdist_utils.py
pytest_robotframework/_internal/robot/__init__.py
pytest_robotframework/_internal/robot/library.py
pytest_robotframework/_internal/robot/listeners_and_suite_visitors.py
pytest_robotframework/_internal/robot/utils.py
pytest_robotframework/_internal/utils.py
pytest_robotframework/py.typed
pytest_robotframework-4.6.2.dist-info/WHEEL
pytest_robotframework-4.6.2.dist-info/entry_points.txt
pytest_robotframework-4.6.2.dist-info/METADATA
pytest_robotframework-4.6.2.dist-info/RECORD
