Metadata-Version: 2.3
Name: pytest_robotframework
Version: 4.6.2
Summary: a pytest plugin that can run both python and robotframework tests while generating robot reports for them
Author: DetachHead
Author-email: DetachHead <detachhead@users.noreply.github.com>
License: MIT
Requires-Dist: ansi2html>=1.9.1
Requires-Dist: pluggy
Requires-Dist: pytest>=7,<10
Requires-Dist: robotframework>=6.1,<8.0.0
Requires-Python: >=3.10, <4.0
Project-URL: repository, https://github.com/detachhead/pytest-robotframework
